cardanoscan/__init__.py
cardanoscan/config.py
cardanoscan/exceptions.py
cardanoscan/utils.py
cardanoscan/apis/__init__.py
cardanoscan/apis/address.py
cardanoscan/apis/assets.py
cardanoscan/apis/block.py
cardanoscan/apis/governance.py
cardanoscan/apis/network.py
cardanoscan/apis/pool.py
cardanoscan/apis/reward_account.py
cardanoscan/apis/stats.py
cardanoscan/apis/transaction.py
cardanoscan/apis/utxo.py
cardanoscan/apis/votes.py
cardanoscan_python-0.0.2.dist-info/licenses/LICENSE
cardanoscan_python-0.0.2.dist-info/METADATA
cardanoscan_python-0.0.2.dist-info/WHEEL
cardanoscan_python-0.0.2.dist-info/top_level.txt
cardanoscan_python-0.0.2.dist-info/RECORD
