Metadata-Version: 2.4
Name: cardanoscan-python
Version: 0.0.2
Summary: Python SDK for Cardanoscan API
License-Expression: Apache-2.0
Project-URL: Homepage, https://cardanoscan.io/api
Project-URL: Documentation, https://docs.cardanoscan.io
Project-URL: Repository, https://github.com/StricaHQ/cardanoscan-python
Keywords: cardanoscan,cardano,cardano api,stricahq
Requires-Python: >=3.9
License-File: LICENSE
Requires-Dist: httpx>=0.23.0
Provides-Extra: test
Requires-Dist: pytest; extra == "test"
Requires-Dist: pytest-asyncio; extra == "test"
Requires-Dist: respx; extra == "test"
Dynamic: license-file
